earthquake_conservation/__init__.py
earthquake_conservation/main.py
src/__init__.py
src/main.py
earthquake_conservation-0.2.dist-info/METADATA
earthquake_conservation-0.2.dist-info/WHEEL
earthquake_conservation-0.2.dist-info/top_level.txt
earthquake_conservation-0.2.dist-info/RECORD
