Metadata-Version: 2.1
Name: earthquake-conservation
Version: 0.2
Summary: Saving earthquake data in a csv file
Home-page: UNKNOWN
Author: UNKNOWN
Author-email: clashofclansgamerarmoo@gmail.com
License: UNKNOWN
Platform: UNKNOWN
